twilnyx/__init__.py
twilnyx/mappings_full.json
twilnyx-0.3.0.dist-info/METADATA
twilnyx-0.3.0.dist-info/WHEEL
twilnyx-0.3.0.dist-info/licenses/LICENSE
twilnyx-0.3.0.dist-info/RECORD
