Metadata-Version: 2.4
Name: twilnyx
Version: 0.3.0
Summary: Proxy for TwiML to TeXML
Project-URL: Homepage, https://github.com/team-telnyx/twilnyx-python
Project-URL: Bug Tracker, https://github.com/team-telnyx/twilnyx-python/issues
Author-email: Telnyx <support@telnyx.com>
License-File: LICENSE
Classifier: License :: OSI Approved :: MIT License
Classifier: Operating System :: OS Independent
Classifier: Programming Language :: Python :: 3
Requires-Python: >=3.8
Requires-Dist: requests>=2.31.0
Requires-Dist: twilio>=9.0.0
